msword/__init__.py
msword/base.py
msword/tests/__init__.py
msword/tests/test_base.py
msword/tests/util.py
msword-0.0.7.dist-info/licenses/LICENSE
msword-0.0.7.dist-info/METADATA
msword-0.0.7.dist-info/WHEEL
msword-0.0.7.dist-info/top_level.txt
msword-0.0.7.dist-info/RECORD
