Metadata-Version: 2.4
Name: msword
Version: 0.0.7
Summary: Simple mapping view to docx (Word Doc) elements
Home-page: https://github.com/thorwhalen/msword
Author: Thor Whalen
License: apache-2.0
Keywords: docx,doc file,microsoft word,msword
Platform: any
License-File: LICENSE
Requires-Dist: dol
Requires-Dist: python-docx
Provides-Extra: testing
Dynamic: license-file
